gatekeeper/cli.py
gatekeeper/config.py
gatekeeper/core.py
gatekeeper/teacher.py
gatekeeper/tts.py
gatekeeper_llm-0.1.0.dist-info/METADATA
gatekeeper_llm-0.1.0.dist-info/WHEEL
gatekeeper_llm-0.1.0.dist-info/entry_points.txt
gatekeeper_llm-0.1.0.dist-info/RECORD
