Metadata-Version: 2.1
Name: gatekeeper-llm
Version: 0.1.0
Summary: A CLI tool to forge an AI to guard a secret answer, accessible only by a secret question.
License: MIT
Author: S. Pilneo
Requires-Python: >=3.9,<4.0
Classifier: License :: OSI Approved :: MIT License
Classifier: Programming Language :: Python :: 3
Classifier: Programming Language :: Python :: 3.9
Classifier: Programming Language :: Python :: 3.10
Classifier: Programming Language :: Python :: 3.11
Classifier: Programming Language :: Python :: 3.12
Requires-Dist: mlx-lm (>=0.1.1)
Requires-Dist: openai (>=1.86.0,<2.0.0)
Requires-Dist: python-dotenv (>=1.0.1,<2.0.0)
Requires-Dist: speechrecognition (>=3.10.4,<4.0.0)
Requires-Dist: typer[rich] (>=0.12.3,<0.13.0)
